yaqd_pmc/VERSION
yaqd_pmc/__init__.py
yaqd_pmc/__version__.py
yaqd_pmc/_pmc.py
yaqd_pmc/mcapi.py
yaqd_pmc/pmc.avpr
yaqd_pmc/pmc.toml
yaqd_pmc-2025.11.0.dist-info/entry_points.txt
yaqd_pmc-2025.11.0.dist-info/licenses/LICENSE
yaqd_pmc-2025.11.0.dist-info/WHEEL
yaqd_pmc-2025.11.0.dist-info/METADATA
yaqd_pmc-2025.11.0.dist-info/RECORD
